README.md
setup.cfg
setup.py
warpy/__init__.py
warpy/__main__.py
warpy/main.py
warpy/utils.py
warpy.egg-info/PKG-INFO
warpy.egg-info/SOURCES.txt
warpy.egg-info/dependency_links.txt
warpy.egg-info/entry_points.txt
warpy.egg-info/requires.txt
warpy.egg-info/top_level.txt